{"nodes": [{"id": "balance_fix_current_balance_field", "label": "current_balance Field in n8n Payload", "file_type": "rationale", "source_file": "BALANCE_TO_AI_FIX.md", "source_location": null, "source_url": null, "captured_at": null, "author": null, "contributor": null}, {"id": "balance_fix_voice_sessions_table", "label": "voice_sessions DB Table", "file_type": "document", "source_file": "BALANCE_TO_AI_FIX.md", "source_location": null, "source_url": null, "captured_at": null, "author": null, "contributor": null}], "edges": [{"source": "balance_fix_current_balance_field", "target": "complete_overview_voice_webhook", "relation": "rationale_for", "confidence": "EXTRACTED", "confidence_score": 1.0, "source_file": "BALANCE_TO_AI_FIX.md", "source_location": null, "weight": 1.0}, {"source": "balance_fix_current_balance_field", "target": "complete_overview_profiles_table", "relation": "references", "confidence": "EXTRACTED", "confidence_score": 1.0, "source_file": "BALANCE_TO_AI_FIX.md", "source_location": null, "weight": 1.0}, {"source": "balance_fix_current_balance_field", "target": "balance_fix_voice_sessions_table", "relation": "references", "confidence": "EXTRACTED", "confidence_score": 1.0, "source_file": "BALANCE_TO_AI_FIX.md", "source_location": null, "weight": 1.0}], "hyperedges": []}