{"nodes": [{"id": "c_users_inkno_documents_github_ongea_pesa_components_ongea_pesa_global_voice_widget_tsx", "label": "global-voice-widget.tsx", "file_type": "code", "source_file": "C:\\Users\\inkno\\Documents\\GitHub\\ongea-pesa\\components\\ongea-pesa\\global-voice-widget.tsx", "source_location": "L1"}, {"id": "ongea_pesa_global_voice_widget_handlesendtext", "label": "handleSendText()", "file_type": "code", "source_file": "C:\\Users\\inkno\\Documents\\GitHub\\ongea-pesa\\components\\ongea-pesa\\global-voice-widget.tsx", "source_location": "L33"}, {"id": "ongea_pesa_global_voice_widget_handlekeypress", "label": "handleKeyPress()", "file_type": "code", "source_file": "C:\\Users\\inkno\\Documents\\GitHub\\ongea-pesa\\components\\ongea-pesa\\global-voice-widget.tsx", "source_location": "L40"}, {"id": "ongea_pesa_global_voice_widget_handleendcall", "label": "handleEndCall()", "file_type": "code", "source_file": "C:\\Users\\inkno\\Documents\\GitHub\\ongea-pesa\\components\\ongea-pesa\\global-voice-widget.tsx", "source_location": "L47"}], "edges": [{"source": "c_users_inkno_documents_github_ongea_pesa_components_ongea_pesa_global_voice_widget_tsx", "target": "react", "relation": "imports_from", "context": "import", "confidence": "EXTRACTED", "source_file": "C:\\Users\\inkno\\Documents\\GitHub\\ongea-pesa\\components\\ongea-pesa\\global-voice-widget.tsx", "source_location": "L3", "weight": 1.0}, {"source": "c_users_inkno_documents_github_ongea_pesa_components_ongea_pesa_global_voice_widget_tsx", "target": "lucide_react", "relation": "imports_from", "context": "import", "confidence": "EXTRACTED", "source_file": "C:\\Users\\inkno\\Documents\\GitHub\\ongea-pesa\\components\\ongea-pesa\\global-voice-widget.tsx", "source_location": "L4", "weight": 1.0}, {"source": "c_users_inkno_documents_github_ongea_pesa_components_ongea_pesa_global_voice_widget_tsx", "target": "c_users_inkno_documents_github_ongea_pesa_components_ui_button", "relation": "imports_from", "context": "import", "confidence": "EXTRACTED", "source_file": "C:\\Users\\inkno\\Documents\\GitHub\\ongea-pesa\\components\\ongea-pesa\\global-voice-widget.tsx", "source_location": "L5", "weight": 1.0}, {"source": "c_users_inkno_documents_github_ongea_pesa_components_ongea_pesa_global_voice_widget_tsx", "target": "ui_button_button", "relation": "imports", "context": "import", "confidence": "EXTRACTED", "source_file": "C:\\Users\\inkno\\Documents\\GitHub\\ongea-pesa\\components\\ongea-pesa\\global-voice-widget.tsx", "source_location": "L5", "weight": 1.0}, {"source": "c_users_inkno_documents_github_ongea_pesa_components_ongea_pesa_global_voice_widget_tsx", "target": "c_users_inkno_documents_github_ongea_pesa_components_ui_card", "relation": "imports_from", "context": "import", "confidence": "EXTRACTED", "source_file": "C:\\Users\\inkno\\Documents\\GitHub\\ongea-pesa\\components\\ongea-pesa\\global-voice-widget.tsx", "source_location": "L6", "weight": 1.0}, {"source": "c_users_inkno_documents_github_ongea_pesa_components_ongea_pesa_global_voice_widget_tsx", "target": "ui_card_card", "relation": "imports", "context": "import", "confidence": "EXTRACTED", "source_file": "C:\\Users\\inkno\\Documents\\GitHub\\ongea-pesa\\components\\ongea-pesa\\global-voice-widget.tsx", "source_location": "L6", "weight": 1.0}, {"source": "c_users_inkno_documents_github_ongea_pesa_components_ongea_pesa_global_voice_widget_tsx", "target": "ui_card_cardcontent", "relation": "imports", "context": "import", "confidence": "EXTRACTED", "source_file": "C:\\Users\\inkno\\Documents\\GitHub\\ongea-pesa\\components\\ongea-pesa\\global-voice-widget.tsx", "source_location": "L6", "weight": 1.0}, {"source": "c_users_inkno_documents_github_ongea_pesa_components_ongea_pesa_global_voice_widget_tsx", "target": "ui_card_cardheader", "relation": "imports", "context": "import", "confidence": "EXTRACTED", "source_file": "C:\\Users\\inkno\\Documents\\GitHub\\ongea-pesa\\components\\ongea-pesa\\global-voice-widget.tsx", "source_location": "L6", "weight": 1.0}, {"source": "c_users_inkno_documents_github_ongea_pesa_components_ongea_pesa_global_voice_widget_tsx", "target": "c_users_inkno_documents_github_ongea_pesa_components_ui_badge", "relation": "imports_from", "context": "import", "confidence": "EXTRACTED", "source_file": "C:\\Users\\inkno\\Documents\\GitHub\\ongea-pesa\\components\\ongea-pesa\\global-voice-widget.tsx", "source_location": "L7", "weight": 1.0}, {"source": "c_users_inkno_documents_github_ongea_pesa_components_ongea_pesa_global_voice_widget_tsx", "target": "ui_badge_badge", "relation": "imports", "context": "import", "confidence": "EXTRACTED", "source_file": "C:\\Users\\inkno\\Documents\\GitHub\\ongea-pesa\\components\\ongea-pesa\\global-voice-widget.tsx", "source_location": "L7", "weight": 1.0}, {"source": "c_users_inkno_documents_github_ongea_pesa_components_ongea_pesa_global_voice_widget_tsx", "target": "c_users_inkno_documents_github_ongea_pesa_components_ui_input", "relation": "imports_from", "context": "import", "confidence": "EXTRACTED", "source_file": "C:\\Users\\inkno\\Documents\\GitHub\\ongea-pesa\\components\\ongea-pesa\\global-voice-widget.tsx", "source_location": "L8", "weight": 1.0}, {"source": "c_users_inkno_documents_github_ongea_pesa_components_ongea_pesa_global_voice_widget_tsx", "target": "ui_input_input", "relation": "imports", "context": "import", "confidence": "EXTRACTED", "source_file": "C:\\Users\\inkno\\Documents\\GitHub\\ongea-pesa\\components\\ongea-pesa\\global-voice-widget.tsx", "source_location": "L8", "weight": 1.0}, {"source": "c_users_inkno_documents_github_ongea_pesa_components_ongea_pesa_global_voice_widget_tsx", "target": "c_users_inkno_documents_github_ongea_pesa_components_ui_scroll_area", "relation": "imports_from", "context": "import", "confidence": "EXTRACTED", "source_file": "C:\\Users\\inkno\\Documents\\GitHub\\ongea-pesa\\components\\ongea-pesa\\global-voice-widget.tsx", "source_location": "L9", "weight": 1.0}, {"source": "c_users_inkno_documents_github_ongea_pesa_components_ongea_pesa_global_voice_widget_tsx", "target": "ui_scroll_area_scrollarea", "relation": "imports", "context": "import", "confidence": "EXTRACTED", "source_file": "C:\\Users\\inkno\\Documents\\GitHub\\ongea-pesa\\components\\ongea-pesa\\global-voice-widget.tsx", "source_location": "L9", "weight": 1.0}, {"source": "c_users_inkno_documents_github_ongea_pesa_components_ongea_pesa_global_voice_widget_tsx", "target": "c_users_inkno_documents_github_ongea_pesa_contexts_elevenlabscontext", "relation": "imports_from", "context": "import", "confidence": "EXTRACTED", "source_file": "C:\\Users\\inkno\\Documents\\GitHub\\ongea-pesa\\components\\ongea-pesa\\global-voice-widget.tsx", "source_location": "L10", "weight": 1.0}, {"source": "c_users_inkno_documents_github_ongea_pesa_components_ongea_pesa_global_voice_widget_tsx", "target": "contexts_elevenlabscontext_useelevenlabs", "relation": "imports", "context": "import", "confidence": "EXTRACTED", "source_file": "C:\\Users\\inkno\\Documents\\GitHub\\ongea-pesa\\components\\ongea-pesa\\global-voice-widget.tsx", "source_location": "L10", "weight": 1.0}, {"source": "c_users_inkno_documents_github_ongea_pesa_components_ongea_pesa_global_voice_widget_tsx", "target": "ongea_pesa_global_voice_widget_handlesendtext", "relation": "contains", "confidence": "EXTRACTED", "source_file": "C:\\Users\\inkno\\Documents\\GitHub\\ongea-pesa\\components\\ongea-pesa\\global-voice-widget.tsx", "source_location": "L33", "weight": 1.0}, {"source": "c_users_inkno_documents_github_ongea_pesa_components_ongea_pesa_global_voice_widget_tsx", "target": "ongea_pesa_global_voice_widget_handlekeypress", "relation": "contains", "confidence": "EXTRACTED", "source_file": "C:\\Users\\inkno\\Documents\\GitHub\\ongea-pesa\\components\\ongea-pesa\\global-voice-widget.tsx", "source_location": "L40", "weight": 1.0}, {"source": "c_users_inkno_documents_github_ongea_pesa_components_ongea_pesa_global_voice_widget_tsx", "target": "ongea_pesa_global_voice_widget_handleendcall", "relation": "contains", "confidence": "EXTRACTED", "source_file": "C:\\Users\\inkno\\Documents\\GitHub\\ongea-pesa\\components\\ongea-pesa\\global-voice-widget.tsx", "source_location": "L47", "weight": 1.0}, {"source": "ongea_pesa_global_voice_widget_handlekeypress", "target": "ongea_pesa_global_voice_widget_handlesendtext", "relation": "calls", "context": "call", "confidence": "EXTRACTED", "source_file": "C:\\Users\\inkno\\Documents\\GitHub\\ongea-pesa\\components\\ongea-pesa\\global-voice-widget.tsx", "source_location": "L43", "weight": 1.0}], "raw_calls": [{"caller_nid": "ongea_pesa_global_voice_widget_handlesendtext", "callee": "trim", "is_member_call": true, "source_file": "C:\\Users\\inkno\\Documents\\GitHub\\ongea-pesa\\components\\ongea-pesa\\global-voice-widget.tsx", "source_location": "L34"}, {"caller_nid": "ongea_pesa_global_voice_widget_handlesendtext", "callee": "sendMessage", "is_member_call": false, "source_file": "C:\\Users\\inkno\\Documents\\GitHub\\ongea-pesa\\components\\ongea-pesa\\global-voice-widget.tsx", "source_location": "L35"}, {"caller_nid": "ongea_pesa_global_voice_widget_handlesendtext", "callee": "setTextInput", "is_member_call": false, "source_file": "C:\\Users\\inkno\\Documents\\GitHub\\ongea-pesa\\components\\ongea-pesa\\global-voice-widget.tsx", "source_location": "L36"}, {"caller_nid": "ongea_pesa_global_voice_widget_handlekeypress", "callee": "preventDefault", "is_member_call": true, "source_file": "C:\\Users\\inkno\\Documents\\GitHub\\ongea-pesa\\components\\ongea-pesa\\global-voice-widget.tsx", "source_location": "L42"}, {"caller_nid": "ongea_pesa_global_voice_widget_handleendcall", "callee": "endSession", "is_member_call": false, "source_file": "C:\\Users\\inkno\\Documents\\GitHub\\ongea-pesa\\components\\ongea-pesa\\global-voice-widget.tsx", "source_location": "L49"}, {"caller_nid": "ongea_pesa_global_voice_widget_handleendcall", "callee": "log", "is_member_call": true, "source_file": "C:\\Users\\inkno\\Documents\\GitHub\\ongea-pesa\\components\\ongea-pesa\\global-voice-widget.tsx", "source_location": "L50"}, {"caller_nid": "ongea_pesa_global_voice_widget_handleendcall", "callee": "error", "is_member_call": true, "source_file": "C:\\Users\\inkno\\Documents\\GitHub\\ongea-pesa\\components\\ongea-pesa\\global-voice-widget.tsx", "source_location": "L52"}]}